chirho/__init__.py
chirho/counterfactual/__init__.py
chirho/counterfactual/internals.py
chirho/counterfactual/ops.py
chirho/counterfactual/handlers/__init__.py
chirho/counterfactual/handlers/ambiguity.py
chirho/counterfactual/handlers/counterfactual.py
chirho/counterfactual/handlers/selection.py
chirho/dynamical/__init__.py
chirho/dynamical/ops.py
chirho/dynamical/handlers/__init__.py
chirho/dynamical/handlers/interruption.py
chirho/dynamical/handlers/solver.py
chirho/dynamical/handlers/trajectory.py
chirho/dynamical/internals/__init__.py
chirho/dynamical/internals/_utils.py
chirho/dynamical/internals/solver.py
chirho/dynamical/internals/backends/__init__.py
chirho/dynamical/internals/backends/torchdiffeq.py
chirho/explainable/__init__.py
chirho/explainable/ops.py
chirho/explainable/handlers/__init__.py
chirho/explainable/handlers/components.py
chirho/explainable/handlers/explanation.py
chirho/explainable/handlers/preemptions.py
chirho/explainable/internals/__init__.py
chirho/explainable/internals/defaults.py
chirho/indexed/__init__.py
chirho/indexed/handlers.py
chirho/indexed/internals.py
chirho/indexed/ops.py
chirho/interventional/__init__.py
chirho/interventional/handlers.py
chirho/interventional/ops.py
chirho/observational/__init__.py
chirho/observational/internals.py
chirho/observational/ops.py
chirho/observational/handlers/__init__.py
chirho/observational/handlers/condition.py
chirho/observational/handlers/predictive.py
chirho/observational/handlers/soft_conditioning.py
chirho/robust/__init__.py
chirho/robust/ops.py
chirho/robust/handlers/__init__.py
chirho/robust/handlers/cut.py
chirho/robust/handlers/estimators.py
chirho/robust/internals/__init__.py
chirho/robust/internals/linearize.py
chirho/robust/internals/nmc.py
chirho/robust/internals/utils.py
chirho-0.3.0.dist-info/licenses/LICENSE.md
chirho-0.3.0.dist-info/METADATA
chirho-0.3.0.dist-info/WHEEL
chirho-0.3.0.dist-info/top_level.txt
chirho-0.3.0.dist-info/RECORD
