Metadata-Version: 2.4
Name: chirho
Version: 0.3.0
Summary: Causal reasoning
Home-page: https://www.basis.ai/
Author: Basis
License: Apache 2.0
Project-URL: Source, https://github.com/BasisResearch/chirho
Keywords: machine learning statistics probabilistic programming bayesian modeling pytorch
Classifier: Intended Audience :: Developers
Classifier: Intended Audience :: Education
Classifier: Intended Audience :: Science/Research
Classifier: License :: OSI Approved :: Apache Software License
Classifier: Operating System :: POSIX :: Linux
Classifier: Operating System :: MacOS :: MacOS X
Classifier: Programming Language :: Python :: 3.9
Classifier: Programming Language :: Python :: 3.10
Classifier: Programming Language :: Python :: 3.11
Requires-Python: >=3.9
License-File: LICENSE.md
Requires-Dist: pyro-ppl>=1.9.1
Provides-Extra: dynamical
Requires-Dist: torchdiffeq; extra == "dynamical"
Provides-Extra: extras
Requires-Dist: jupyter; extra == "extras"
Requires-Dist: graphviz; extra == "extras"
Requires-Dist: matplotlib; extra == "extras"
Requires-Dist: pandas; extra == "extras"
Requires-Dist: seaborn; extra == "extras"
Requires-Dist: pytorch-lightning; extra == "extras"
Requires-Dist: scikit-image; extra == "extras"
Requires-Dist: tensorboard; extra == "extras"
Requires-Dist: typing_extensions; extra == "extras"
Provides-Extra: test
Requires-Dist: jupyter; extra == "test"
Requires-Dist: graphviz; extra == "test"
Requires-Dist: matplotlib; extra == "test"
Requires-Dist: pandas; extra == "test"
Requires-Dist: seaborn; extra == "test"
Requires-Dist: pytorch-lightning; extra == "test"
Requires-Dist: scikit-image; extra == "test"
Requires-Dist: tensorboard; extra == "test"
Requires-Dist: typing_extensions; extra == "test"
Requires-Dist: torchdiffeq; extra == "test"
Requires-Dist: pytest; extra == "test"
Requires-Dist: pytest-cov; extra == "test"
Requires-Dist: pytest-xdist; extra == "test"
Requires-Dist: mypy==1.10; extra == "test"
Requires-Dist: black; extra == "test"
Requires-Dist: flake8; extra == "test"
Requires-Dist: isort; extra == "test"
Requires-Dist: sphinx==7.1.2; extra == "test"
Requires-Dist: sphinxcontrib-bibtex; extra == "test"
Requires-Dist: sphinxcontrib-jquery; extra == "test"
Requires-Dist: sphinx_rtd_theme==1.3.0; extra == "test"
Requires-Dist: myst_parser; extra == "test"
Requires-Dist: nbsphinx; extra == "test"
Requires-Dist: nbval; extra == "test"
Requires-Dist: nbqa; extra == "test"
Dynamic: author
Dynamic: classifier
Dynamic: description
Dynamic: home-page
Dynamic: keywords
Dynamic: license
Dynamic: license-file
Dynamic: project-url
Dynamic: provides-extra
Dynamic: requires-dist
Dynamic: requires-python
Dynamic: summary
